{"cameraMode":{"drawMode":0,"name":"Shaded","section":"Shading Mode"},"sceneLighting":true,"audioPlay":false,"sceneViewState":{"showFog":true,"showMaterialUpdate":false,"showSkybox":true,"showFlares":true,"showImageEffects":true,"showParticleSystems":true},"in2DMode":false,"pivot":{"x":149.01284790039063,"y":120.80992126464844,"z":255.58445739746095},"rotation":{"x":0.4412239193916321,"y":0.5540850758552551,"z":-0.44843199849128725,"w":0.5451789498329163},"size":95.178466796875,"orthographic":false}